calculate_lib/__init__.py
calculate_lib/operations.py
calculate_lib-0.1.dist-info/METADATA
calculate_lib-0.1.dist-info/WHEEL
calculate_lib-0.1.dist-info/top_level.txt
calculate_lib-0.1.dist-info/RECORD
