Metadata-Version: 2.1
Name: calculate-lib
Version: 0.1
Summary: A simple library for basic arithmetic operations
Home-page: https://github.com/yourusername/calculate-lib
Author: Your Name
Author-email: your.email@example.com
Classifier: Programming Language :: Python :: 3
Classifier: License :: OSI Approved :: MIT License
Classifier: Operating System :: OS Independent
Requires-Python: >=3.6
